{
 "bundle_id": "eb_9d56d2",
 "question": "Will the swing senators join the bipartisan compromise bloc?",
 "as_of": 1685577600.0,
 "compiler_plan_hash": "24f0a9096fd7",
 "schema_version": "evidence-bundle-v2.0",
 "evidence_system_version": "phase2-1.0",
 "prior_bundle_hash": "",
 "version": 1,
 "requirements": [
  {
   "requirement_id": "req_7b5a54c3ee",
   "claim_or_quantity": "yes if at least three swing senators (as identified by media and whip counts) announce support for the compromise bloc by 2023-07-15, else no",
   "why_relevant": "the terminal outcome standing as of the question date sets the base rate",
   "affected_component": "terminal_outcome",
   "expected_sensitivity": 1.0,
   "expected_voi": 1.0,
   "preferred_source_types": [
    "news",
    "wire"
   ],
   "fallback_source_types": [
    "wikipedia_revision"
   ],
   "disallowed_source_types": [],
   "as_of_constraint": "2023-06-01",
   "event_time_scope": "",
   "publication_time_scope": "paired_after_before",
   "geographic_scope": "",
   "jurisdiction": "",
   "entity_scope": [
    "senator_murkowski",
    "senator_collins",
    "senator_sinema",
    "senator_manchin"
   ],
   "structured_fields": [],
   "actor_visibility_assumption": "public",
   "absence_informative": true,
   "retrieval_cost_estimate": 1.0,
   "stopping_criteria": "coverage>=1 claim or 2 queries",
   "missing_consequence": "widen prior; lower support grade",
   "uncertainty_if_unmet": "broad",
   "status": "open"
  },
  {
   "requirement_id": "req_5075cabb5a",
   "claim_or_quantity": "value/context of senator_murkowski.private_lean",
   "why_relevant": "high-sensitivity latent (0.90) driving the outcome distribution",
   "affected_component": "senator_murkowski.private_lean",
   "expected_sensitivity": 0.9,
   "expected_voi": 0.9,
   "preferred_source_types": [
    "news",
    "wire"
   ],
   "fallback_source_types": [
    "wikipedia_revision"
   ],
   "disallowed_source_types": [],
   "as_of_constraint": "2023-06-01",
   "event_time_scope": "",
   "publication_time_scope": "paired_after_before",
   "geographic_scope": "",
   "jurisdiction": "",
   "entity_scope": [],
   "structured_fields": [],
   "actor_visibility_assumption": "public",
   "absence_informative": false,
   "retrieval_cost_estimate": 1.0,
   "stopping_criteria": "coverage>=1 claim or 2 queries",
   "missing_consequence": "widen prior; lower support grade",
   "uncertainty_if_unmet": "broad",
   "status": "open"
  },
  {
   "requirement_id": "req_8dea3252b6",
   "claim_or_quantity": "value/context of senator_collins.private_lean",
   "why_relevant": "high-sensitivity latent (0.90) driving the outcome distribution",
   "affected_component": "senator_collins.private_lean",
   "expected_sensitivity": 0.9,
   "expected_voi": 0.9,
   "preferred_source_types": [
    "news",
    "wire"
   ],
   "fallback_source_types": [
    "wikipedia_revision"
   ],
   "disallowed_source_types": [],
   "as_of_constraint": "2023-06-01",
   "event_time_scope": "",
   "publication_time_scope": "paired_after_before",
   "geographic_scope": "",
   "jurisdiction": "",
   "entity_scope": [],
   "structured_fields": [],
   "actor_visibility_assumption": "public",
   "absence_informative": false,
   "retrieval_cost_estimate": 1.0,
   "stopping_criteria": "coverage>=1 claim or 2 queries",
   "missing_consequence": "widen prior; lower support grade",
   "uncertainty_if_unmet": "broad",
   "status": "open"
  },
  {
   "requirement_id": "req_eb46c87b9d",
   "claim_or_quantity": "value/context of senator_sinema.private_lean",
   "why_relevant": "high-sensitivity latent (0.90) driving the outcome distribution",
   "affected_component": "senator_sinema.private_lean",
   "expected_sensitivity": 0.9,
   "expected_voi": 0.9,
   "preferred_source_types": [
    "news",
    "wire"
   ],
   "fallback_source_types": [
    "wikipedia_revision"
   ],
   "disallowed_source_types": [],
   "as_of_constraint": "2023-06-01",
   "event_time_scope": "",
   "publication_time_scope": "paired_after_before",
   "geographic_scope": "",
   "jurisdiction": "",
   "entity_scope": [],
   "structured_fields": [],
   "actor_visibility_assumption": "public",
   "absence_informative": false,
   "retrieval_cost_estimate": 1.0,
   "stopping_criteria": "coverage>=1 claim or 2 queries",
   "missing_consequence": "widen prior; lower support grade",
   "uncertainty_if_unmet": "broad",
   "status": "open"
  },
  {
   "requirement_id": "req_87d7258e36",
   "claim_or_quantity": "evidence discriminating structural hypothesis party_discipline_dominates",
   "why_relevant": "a fact that reweights competing structural hypotheses materially changes the outcome",
   "affected_component": "structural_hypothesis:party_discipline_dominates",
   "expected_sensitivity": 0.8,
   "expected_voi": 0.8,
   "preferred_source_types": [
    "news",
    "wire"
   ],
   "fallback_source_types": [
    "wikipedia_revision"
   ],
   "disallowed_source_types": [],
   "as_of_constraint": "2023-06-01",
   "event_time_scope": "",
   "publication_time_scope": "paired_after_before",
   "geographic_scope": "",
   "jurisdiction": "",
   "entity_scope": [],
   "structured_fields": [],
   "actor_visibility_assumption": "public",
   "absence_informative": false,
   "retrieval_cost_estimate": 1.0,
   "stopping_criteria": "coverage>=1 claim or 2 queries",
   "missing_consequence": "widen prior; lower support grade",
   "uncertainty_if_unmet": "broad",
   "status": "open"
  },
  {
   "requirement_id": "req_e2aaf2e192",
   "claim_or_quantity": "evidence discriminating structural hypothesis constituency_driven",
   "why_relevant": "a fact that reweights competing structural hypotheses materially changes the outcome",
   "affected_component": "structural_hypothesis:constituency_driven",
   "expected_sensitivity": 0.8,
   "expected_voi": 0.8,
   "preferred_source_types": [
    "news",
    "wire"
   ],
   "fallback_source_types": [
    "wikipedia_revision"
   ],
   "disallowed_source_types": [],
   "as_of_constraint": "2023-06-01",
   "event_time_scope": "",
   "publication_time_scope": "paired_after_before",
   "geographic_scope": "",
   "jurisdiction": "",
   "entity_scope": [],
   "structured_fields": [],
   "actor_visibility_assumption": "public",
   "absence_informative": false,
   "retrieval_cost_estimate": 1.0,
   "stopping_criteria": "coverage>=1 claim or 2 queries",
   "missing_consequence": "widen prior; lower support grade",
   "uncertainty_if_unmet": "broad",
   "status": "open"
  },
  {
   "requirement_id": "req_e69c5c3dbd",
   "claim_or_quantity": "decision rules / process of us_senate",
   "why_relevant": "institutional rules determine which actions are feasible and when the outcome resolves",
   "affected_component": "us_senate",
   "expected_sensitivity": 0.7,
   "expected_voi": 0.7,
   "preferred_source_types": [
    "official_filing",
    "regulatory",
    "news"
   ],
   "fallback_source_types": [
    "wikipedia_revision"
   ],
   "disallowed_source_types": [],
   "as_of_constraint": "2023-06-01",
   "event_time_scope": "",
   "publication_time_scope": "",
   "geographic_scope": "",
   "jurisdiction": "",
   "entity_scope": [],
   "structured_fields": [],
   "actor_visibility_assumption": "public",
   "absence_informative": true,
   "retrieval_cost_estimate": 1.0,
   "stopping_criteria": "coverage>=1 claim or 2 queries",
   "missing_consequence": "widen prior; lower support grade",
   "uncertainty_if_unmet": "broad",
   "status": "open"
  },
  {
   "requirement_id": "req_51671cc8cf",
   "claim_or_quantity": "decision rules / process of bipartisan_bloc",
   "why_relevant": "institutional rules determine which actions are feasible and when the outcome resolves",
   "affected_component": "bipartisan_bloc",
   "expected_sensitivity": 0.7,
   "expected_voi": 0.7,
   "preferred_source_types": [
    "official_filing",
    "regulatory",
    "news"
   ],
   "fallback_source_types": [
    "wikipedia_revision"
   ],
   "disallowed_source_types": [],
   "as_of_constraint": "2023-06-01",
   "event_time_scope": "",
   "publication_time_scope": "",
   "geographic_scope": "",
   "jurisdiction": "",
   "entity_scope": [],
   "structured_fields": [],
   "actor_visibility_assumption": "public",
   "absence_informative": true,
   "retrieval_cost_estimate": 1.0,
   "stopping_criteria": "coverage>=1 claim or 2 queries",
   "missing_consequence": "widen prior; lower support grade",
   "uncertainty_if_unmet": "broad",
   "status": "open"
  }
 ],
 "retrieval_plan": [
  {
   "requirement_id": "req_7b5a54c3ee",
   "terms": "swing senators join bipartisan compromise bloc senator murkowski senator collins senator sinema",
   "after": "2023-01-02",
   "before": "2023-06-01",
   "preferred": [
    "news",
    "wire"
   ]
  },
  {
   "requirement_id": "req_5075cabb5a",
   "terms": "senator murkowski private lean",
   "after": "2023-01-02",
   "before": "2023-06-01",
   "preferred": [
    "news",
    "wire"
   ]
  },
  {
   "requirement_id": "req_8dea3252b6",
   "terms": "senator collins private lean",
   "after": "2023-01-02",
   "before": "2023-06-01",
   "preferred": [
    "news",
    "wire"
   ]
  }
 ],
 "retrieval_traces": [
  {
   "connector_id": "google_news_rss",
   "connector_version": "1.0",
   "requirement_id": "req_7b5a54c3ee",
   "logical_query": "swing senators join bipartisan compromise bloc senator murkowski senator collins senator sinema after:2023-01-02 before:2023-06-01",
   "wire_url": "https://news.google.com/rss/search?q=swing+senators+join+bipartisan+compromise+bloc+senator+murkowski+senator+collins+senator+sinema+after%3A2023-01-02+before%3A2023-06-01&hl=en-US&gl=US&ceid=US%3Aen",
   "after_date": "2023-01-02",
   "before_date": "2023-06-01",
   "retrieved_at": 1783907902.7314372,
   "status_code": 200,
   "redirects": [],
   "response_headers": {
    "Content-Type": "application/xml; charset=utf-8",
    "Cache-Control": "no-cache, no-store, max-age=0, must-revalidate",
    "Pragma": "no-cache",
    "Expires": "Mon, 01 Jan 1990 00:00:00 GMT",
    "Date": "Mon, 13 Jul 2026 01:58:23 GMT",
    "Strict-Transport-Security": "max-age=31536000",
    "Cross-Origin-Opener-Policy": "same-origin-allow-popups",
    "Content-Security-Policy": "script-src 'unsafe-inline' https: http:;object-src 'none';base-uri 'self';report-uri /_/DotsSplashUi/cspreport;worker-src 'self'",
    "Permissions-Policy": "ch-ua-arch=*, ch-ua-bitness=*, ch-ua-full-version=*, ch-ua-full-version-list=*, ch-ua-model=*, ch-ua-wow64=*, ch-ua-form-factors=*, ch-ua-platform=*, ch-ua-platform-version=*",
    "Cross-Origin-Resource-Policy": "same-site",
    "Accept-CH": "Sec-CH-UA-Arch, Sec-CH-UA-Bitness, Sec-CH-UA-Full-Version, Sec-CH-UA-Full-Version-List, Sec-CH-UA-Model, Sec-CH-UA-WoW64, Sec-CH-UA-Form-Factors, Sec-CH-UA-Platform, Sec-CH-UA-Platform-Version",
    "reporting-endpoints": "default=\"/_/DotsSplashUi/web-reports?context=eJzjytDikmLw1pBiSO44w5AKxHVA3ADEfBXPmVpvnmOdDMQli86zNgFxFxDPAGJDhUus9kB8Of0Sa5HEFdYGIP5UdYNVoPoG67diXzaWEiB-689mGhLI5gzEWzSD2YR4OPb3XLzEJjDj7u1uRiXlpPzC-JT8kuLigpzE4ozi1KKy1KJ4IwMjMwNzAzM9A5P4AgMAh6w6Rw\"",
    "Server": "ESF",
    "X-XSS-Protection": "0",
    "X-Frame-Options": "SAMEORIGIN",
    "X-Content-Type-Options": "nosniff",
    "Accept-Ranges": "none",
    "Vary": "Sec-Fetch-Dest, Sec-Fetch-Mode, Sec-Fetch-Site,Accept-Encoding",
    "Connection": "close"
   },
   "raw_content_hash": "ed4ccaa49001b361173c884d57a02362f3fea806d7815ce3092578ace166c3e5",
   "n_bytes": 1355,
   "feed_parser_version": "gnews-rss-parser-1.0",
   "n_items": 0,
   "connector_status": "zero_results",
   "error": "",
   "latency_s": 0.467
  },
  {
   "connector_id": "google_news_rss",
   "connector_version": "1.0",
   "requirement_id": "req_5075cabb5a",
   "logical_query": "senator murkowski private lean after:2023-01-02 before:2023-06-01",
   "wire_url": "https://news.google.com/rss/search?q=senator+murkowski+private+lean+after%3A2023-01-02+before%3A2023-06-01&hl=en-US&gl=US&ceid=US%3Aen",
   "after_date": "2023-01-02",
   "before_date": "2023-06-01",
   "retrieved_at": 1783907903.2002554,
   "status_code": 200,
   "redirects": [],
   "response_headers": {
    "Content-Type": "application/xml; charset=utf-8",
    "Cache-Control": "no-cache, no-store, max-age=0, must-revalidate",
    "Pragma": "no-cache",
    "Expires": "Mon, 01 Jan 1990 00:00:00 GMT",
    "Date": "Mon, 13 Jul 2026 01:58:23 GMT",
    "Strict-Transport-Security": "max-age=31536000",
    "Cross-Origin-Opener-Policy": "same-origin-allow-popups",
    "Content-Security-Policy": "script-src 'unsafe-inline' https: http:;object-src 'none';base-uri 'self';report-uri /_/DotsSplashUi/cspreport;worker-src 'self'",
    "Permissions-Policy": "ch-ua-arch=*, ch-ua-bitness=*, ch-ua-full-version=*, ch-ua-full-version-list=*, ch-ua-model=*, ch-ua-wow64=*, ch-ua-form-factors=*, ch-ua-platform=*, ch-ua-platform-version=*",
    "Cross-Origin-Resource-Policy": "same-site",
    "Accept-CH": "Sec-CH-UA-Arch, Sec-CH-UA-Bitness, Sec-CH-UA-Full-Version, Sec-CH-UA-Full-Version-List, Sec-CH-UA-Model, Sec-CH-UA-WoW64, Sec-CH-UA-Form-Factors, Sec-CH-UA-Platform, Sec-CH-UA-Platform-Version",
    "reporting-endpoints": "default=\"/_/DotsSplashUi/web-reports?context=eJzjytDikmII0pBiSO44w5ACxHVA3AjEfBXPmVpvnmOdDMQli86zNgFxFxDPAGJDhUus9kB8Of0Sa5HEFdYGIP5UdYNVoPoG67diXzaWEiB-689mGhLI5gzEWzSD2YR4OPb3XLzEJnDj0IXbTErKSfmF8Sn5JcXFBTmJxRnFqUVlqUXxRgZGZgbmBmZ6BibxBQYAnJA6uQ\"",
    "Server": "ESF",
    "X-XSS-Protection": "0",
    "X-Frame-Options": "SAMEORIGIN",
    "X-Content-Type-Options": "nosniff",
    "Accept-Ranges": "none",
    "Vary": "Sec-Fetch-Dest, Sec-Fetch-Mode, Sec-Fetch-Site,Accept-Encoding",
    "Connection": "close"
   },
   "raw_content_hash": "2e3d505ec24b0a4a5e74cfbe47295e91c940cfb0b67932d8d552232c86369c2a",
   "n_bytes": 1225,
   "feed_parser_version": "gnews-rss-parser-1.0",
   "n_items": 0,
   "connector_status": "zero_results",
   "error": "",
   "latency_s": 0.437
  },
  {
   "connector_id": "google_news_rss",
   "connector_version": "1.0",
   "requirement_id": "req_8dea3252b6",
   "logical_query": "senator collins private lean after:2023-01-02 before:2023-06-01",
   "wire_url": "https://news.google.com/rss/search?q=senator+collins+private+lean+after%3A2023-01-02+before%3A2023-06-01&hl=en-US&gl=US&ceid=US%3Aen",
   "after_date": "2023-01-02",
   "before_date": "2023-06-01",
   "retrieved_at": 1783907903.6390924,
   "status_code": 200,
   "redirects": [],
   "response_headers": {
    "Content-Type": "application/xml; charset=utf-8",
    "Cache-Control": "no-cache, no-store, max-age=0, must-revalidate",
    "Pragma": "no-cache",
    "Expires": "Mon, 01 Jan 1990 00:00:00 GMT",
    "Date": "Mon, 13 Jul 2026 01:58:24 GMT",
    "Strict-Transport-Security": "max-age=31536000",
    "Permissions-Policy": "ch-ua-arch=*, ch-ua-bitness=*, ch-ua-full-version=*, ch-ua-full-version-list=*, ch-ua-model=*, ch-ua-wow64=*, ch-ua-form-factors=*, ch-ua-platform=*, ch-ua-platform-version=*",
    "Cross-Origin-Opener-Policy": "same-origin-allow-popups",
    "Content-Security-Policy": "require-trusted-types-for 'script';report-uri /_/DotsSplashUi/cspreport",
    "Cross-Origin-Resource-Policy": "same-site",
    "Accept-CH": "Sec-CH-UA-Arch, Sec-CH-UA-Bitness, Sec-CH-UA-Full-Version, Sec-CH-UA-Full-Version-List, Sec-CH-UA-Model, Sec-CH-UA-WoW64, Sec-CH-UA-Form-Factors, Sec-CH-UA-Platform, Sec-CH-UA-Platform-Version",
    "reporting-endpoints": "default=\"/_/DotsSplashUi/web-reports?context=eJzjStHikmII0JBiSO44w5ACxHVA3AjErTfPsU4G4pJF51mbgLgLiGcAsaHCJVZ7IL6cfom1SOIKawMQf6q6wSpQfYP1W7EvG0sJEL_1ZzMNCWRzBuItmsFsQtwcB3ouXmITuPFnZrySclJ-YXxKfklxcUFOYnFGcWpRWWpRvJGBkZmBuYGZnoFJfIEBAH7OOMk\"",
    "Server": "ESF",
    "X-XSS-Protection": "0",
    "X-Frame-Options": "SAMEORIGIN",
    "X-Content-Type-Options": "nosniff",
    "Accept-Ranges": "none",
    "Vary": "Sec-Fetch-Dest, Sec-Fetch-Mode, Sec-Fetch-Site,Accept-Encoding",
    "Connection": "close"
   },
   "raw_content_hash": "e3c01c05c993cd295bfbd3eabdab0e0cd2a1882271b3e4e472ccbaa2276ae383",
   "n_bytes": 1221,
   "feed_parser_version": "gnews-rss-parser-1.0",
   "n_items": 0,
   "connector_status": "zero_results",
   "error": "",
   "latency_s": 0.466
  }
 ],
 "raw_content_refs": [],
 "documents": [],
 "claims": [],
 "entities": [],
 "temporal_records": {},
 "dependence_groups": [],
 "contradiction_graph": [],
 "actor_visibility": [],
 "leakage_flags": [],
 "included_claim_ids": [],
 "excluded_claim_ids": [],
 "suspicious_claim_ids": [],
 "requirement_coverage": {
  "req_7b5a54c3ee": {
   "status": "unmet",
   "n_claims": 0,
   "n_included": 0
  },
  "req_5075cabb5a": {
   "status": "unmet",
   "n_claims": 0,
   "n_included": 0
  },
  "req_8dea3252b6": {
   "status": "unmet",
   "n_claims": 0,
   "n_included": 0
  },
  "req_eb46c87b9d": {
   "status": "unmet",
   "n_claims": 0,
   "n_included": 0
  },
  "req_87d7258e36": {
   "status": "unmet",
   "n_claims": 0,
   "n_included": 0
  },
  "req_e2aaf2e192": {
   "status": "unmet",
   "n_claims": 0,
   "n_included": 0
  },
  "req_e69c5c3dbd": {
   "status": "unmet",
   "n_claims": 0,
   "n_included": 0
  },
  "req_51671cc8cf": {
   "status": "unmet",
   "n_claims": 0,
   "n_included": 0
  }
 },
 "missing_evidence": [
  "req_7b5a54c3ee",
  "req_5075cabb5a",
  "req_8dea3252b6",
  "req_eb46c87b9d",
  "req_87d7258e36",
  "req_e2aaf2e192",
  "req_e69c5c3dbd",
  "req_51671cc8cf"
 ],
 "evidence_uncertainty": {
  "n_independent_sources": 0,
  "n_contradictions": 0,
  "n_documents": 0
 },
 "connector_failures": [],
 "cost_usd": 0.0,
 "latency_s": 1.376,
 "seed": 7,
 "versions": {
  "evidence_system": "phase2-1.0",
  "temporal": "1.0",
  "claims": "claims-extract-1.0"
 },
 "frozen": true,
 "_hash": "3d828a78012438ab",
 "bundle_hash": "3d828a78012438ab",
 "_persisted_at": "2026-07-13T01:58:24Z"
}