{
 "domain": "protest",
 "question": "Will the teachers' strike spread to neighboring districts within two weeks?",
 "as_of": "2023-05-01",
 "horizon": "2023-05-15",
 "compiled": true,
 "abstained": false,
 "abstain_reason": "",
 "executed_e2e": true,
 "materialize_abstained": false,
 "n_accepted_mech": 1,
 "n_rejected_mech": 3,
 "mechanisms": [
  "agent_decision"
 ],
 "all_mech_executable": true,
 "readout_var": "strike_spread_flag",
 "readout_resolves": true,
 "n_entities": 3,
 "n_institutions": 3,
 "n_populations": 3,
 "n_latents": 2,
 "provenance_ok": true,
 "n_omissions": 9,
 "terminal_distribution": null,
 "error": "",
 "latency_s": 7.79
}