{
 "domain": "fundraising",
 "question": "Will the crowdfunding project reach its funding target before the deadline?",
 "as_of": "2023-05-01",
 "horizon": "2023-06-01",
 "compiled": true,
 "abstained": false,
 "abstain_reason": "",
 "executed_e2e": true,
 "materialize_abstained": false,
 "n_accepted_mech": 2,
 "n_rejected_mech": 0,
 "mechanisms": [
  "poisson_arrival",
  "resource_update"
 ],
 "all_mech_executable": true,
 "readout_var": "campaign.pledged",
 "readout_resolves": true,
 "n_entities": 1,
 "n_institutions": 0,
 "n_populations": 1,
 "n_latents": 0,
 "provenance_ok": true,
 "n_omissions": 3,
 "terminal_distribution": null,
 "error": "",
 "latency_s": 5.2
}