{
 "version": "family-survival-1.0",
 "fit_on": "calibration split only",
 "global_hazards": [
  0.0165,
  0.0,
  0.0168,
  0.0342,
  0.0619
 ],
 "families": {
  "generic": {
   "n": 112,
   "hazards": [
    0.0178,
    0.0,
    0.0181,
    0.0281,
    0.0483
   ]
  },
  "announcement_or_visit": {
   "n": 2,
   "hazards": [
    0.0124,
    0.0,
    0.0126,
    0.0256,
    0.1715
   ]
  },
  "meeting_or_deal_by_date": {
   "n": 1,
   "hazards": [
    0.0142,
    0.0,
    0.0144,
    0.1722,
    0.0531
   ]
  },
  "sports_match": {
   "n": 2,
   "hazards": [
    0.0124,
    0.0,
    0.0126,
    0.0256,
    0.0465
   ]
  },
  "personnel_out_by_date": {
   "n": 1,
   "hazards": [
    0.0142,
    0.0,
    0.0144,
    0.0293,
    0.0531
   ]
  },
  "price_threshold": {
   "n": 2,
   "hazards": [
    0.0124,
    0.0,
    0.0126,
    0.0256,
    0.1715
   ]
  },
  "approval_or_passage": {
   "n": 1,
   "hazards": [
    0.0142,
    0.0,
    0.0144,
    0.0293,
    0.0531
   ]
  }
 },
 "walk_forward": {
  "snapshot_boundary": "2025-04-01",
  "n_training_rows": 121,
  "latest_included_resolution_ts": 1743422400.0,
  "min_source_ts": 1719619202.0,
  "fitted_at": 1784308530.8965054,
  "source_hash": "a94d61be110aece1",
  "training_code": "swm.world_model_v2.event_time.fit_survival_pack"
 }
}